.gitignore
CMakeLists.txt
LICENSE
MANIFEST.in
README.md
pyproject.toml
setup.py
.github/workflows/build_ubuntu18.yml
.github/workflows/build_ubuntu20.yml
.github/workflows/build_ubuntu22.yml
.github/workflows/pypi_test_ubuntu18.yml
.github/workflows/pypi_test_ubuntu20.yml
.github/workflows/pypi_test_ubuntu22.yml
.github/workflows/pypi_ubuntu18.yml
.github/workflows/pypi_ubuntu20.yml
.github/workflows/pypi_ubuntu22.yml
.github/workflows/test_ubuntu18.yml
.github/workflows/test_ubuntu20.yml
.github/workflows/test_ubuntu22.yml
ceres_raytracer.egg-info/PKG-INFO
ceres_raytracer.egg-info/SOURCES.txt
ceres_raytracer.egg-info/dependency_links.txt
ceres_raytracer.egg-info/not-zip-safe
ceres_raytracer.egg-info/requires.txt
ceres_raytracer.egg-info/top_level.txt
crt/__init__.py
crt/_pybind_convert.py
crt/_validate_values.py
crt/_version.py
crt/body_fixed.py
crt/cameras.py
crt/entity.py
crt/lidars.py
crt/lights.py
crt/rendering.py
crt/rigid_body.py
crt/rotations.py
doc/Makefile
doc/ceres_rt.rst
doc/conf.py
doc/demos.rst
doc/get-pip.py
doc/index.rst
doc/installation.rst
doc/license.rst
doc/make.bat
doc/_static/ceres_white_long.png
doc/modules/body_fixed.rst
doc/modules/cameras.rst
doc/modules/entity.rst
doc/modules/lights.rst
doc/modules/rendering.rst
doc/modules/rigid_body.rst
doc/modules/rotations.rst
doc/modules/body_fixed/body_fixed_entity.rst
doc/modules/body_fixed/body_fixed_group.rst
doc/modules/cameras/pinhole_camera.rst
doc/modules/lights/point_light.rst
doc/modules/lights/square_light.rst
lib/CMakeLists.txt
lib/bvh/CMakeLists.txt
lib/bvh/binned_sah_builder.hpp
lib/bvh/bottom_up_algorithm.hpp
lib/bvh/bounding_box.hpp
lib/bvh/bvh.hpp
lib/bvh/heuristic_primitive_splitter.hpp
lib/bvh/hierarchy_refitter.hpp
lib/bvh/leaf_collapser.hpp
lib/bvh/linear_bvh_builder.hpp
lib/bvh/locally_ordered_clustering_builder.hpp
lib/bvh/morton.hpp
lib/bvh/morton_code_based_builder.hpp
lib/bvh/node_intersectors.hpp
lib/bvh/node_layout_optimizer.hpp
lib/bvh/parallel_reinsertion_optimizer.hpp
lib/bvh/platform.hpp
lib/bvh/prefix_sum.hpp
lib/bvh/primitive_intersectors.hpp
lib/bvh/radix_sort.hpp
lib/bvh/ray.hpp
lib/bvh/sah_based_algorithm.hpp
lib/bvh/single_ray_traverser.hpp
lib/bvh/spatial_split_bvh_builder.hpp
