Metadata-Version: 2.1
Name: ceres-raytracer
Version: 0.6a3
Summary: CERES Ray Tracer
Home-page: UNKNOWN
Author: Chris Gnam
Author-email: crgnam@buffalo.edu
License: UNKNOWN
Project-URL: Documentation, https://docs.crt.ceresnavigation.org
Project-URL: Source, https://github.com/ceres-navigation/ceres-raytracer
Project-URL: Tracker, https://github.com/ceres-navigation/ceres-raytracer/issues
Platform: UNKNOWN
Requires-Python: >=3.6
License-File: LICENSE
